sitTools/__init__.py
sitTools/cTools.py
sitTools/gTools.py
sitTools/sTools.py
sitTools/tools.py
sitTools-0.0.8.dist-info/LICENSE
sitTools-0.0.8.dist-info/METADATA
sitTools-0.0.8.dist-info/WHEEL
sitTools-0.0.8.dist-info/top_level.txt
sitTools-0.0.8.dist-info/RECORD
