Metadata-Version: 2.1
Name: sitTools
Version: 0.0.8
Summary: Useful function tools for SIT project use.
Home-page: https://github.com/sit-sys/sitTools
Author: Andy Yang
Author-email: andy.yang@twsit.com
License: MIT
Download-URL: https://pypi.org/project/sitTools/
Platform: UNKNOWN
Classifier: Programming Language :: Python :: 3.7
Classifier: Programming Language :: Python :: 3.8
Classifier: Programming Language :: Python :: 3.9
Classifier: Programming Language :: Python :: 3.10
Classifier: Programming Language :: Python :: 3.11
Requires-Python: >=3.8
Requires-Dist: configparser
Requires-Dist: numpy
Requires-Dist: pandas
Provides-Extra: dev
